{"task-228": {"id": "task-228", "runtime": 56751, "cores": 100, "data_deps": {}}, "task-229": {"id": "task-229", "runtime": 96316, "cores": 100, "data_deps": {}}, "task-230": {"id": "task-230", "runtime": 112961, "cores": 100, "data_deps": {}}, "task-231": {"id": "task-231", "runtime": 117386, "cores": 100, "data_deps": {}}, "task-232": {"id": "task-232", "runtime": 180202, "cores": 1000, "data_deps": {"task-228": 100, "task-229": 100, "task-230": 100, "task-231": 100}}, "task-233": {"id": "task-233", "runtime": 346, "cores": 200, "data_deps": {"task-228": 100, "task-229": 100, "task-230": 100, "task-231": 100}}, "task-234": {"id": "task-234", "runtime": 169, "cores": 200, "data_deps": {"task-228": 100, "task-229": 100, "task-230": 100, "task-231": 100}}, "task-235": {"id": "task-235", "runtime": 77399, "cores": 200, "data_deps": {"task-232": 1000, "task-233": 200, "task-234": 200}}, "task-236": {"id": "task-236", "runtime": 77252, "cores": 200, "data_deps": {"task-232": 1000, "task-233": 200, "task-234": 200}}, "task-237": {"id": "task-237", "runtime": 314, "cores": 1000, "data_deps": {"task-232": 1000, "task-233": 200, "task-234": 200}}, "task-238": {"id": "task-238", "runtime": 395, "cores": 1000, "data_deps": {"task-235": 200, "task-236": 200, "task-237": 1000}}, "task-239": {"id": "task-239", "runtime": 177554, "cores": 1000, "data_deps": {"task-235": 200, "task-236": 200, "task-237": 1000}}, "task-240": {"id": "task-240", "runtime": 1986, "cores": 1000, "data_deps": {"task-235": 200, "task-236": 200, "task-237": 1000}}}