{"task-3033": {"id": "task-3033", "runtime": 135, "cores": 300, "data_deps": {}}, "task-3034": {"id": "task-3034", "runtime": 166, "cores": 300, "data_deps": {}}, "task-3035": {"id": "task-3035", "runtime": 77, "cores": 300, "data_deps": {}}, "task-3036": {"id": "task-3036", "runtime": 200, "cores": 300, "data_deps": {}}, "task-3037": {"id": "task-3037", "runtime": 50, "cores": 300, "data_deps": {"task-3033": 300, "task-3034": 300, "task-3035": 300, "task-3036": 300}}, "task-3038": {"id": "task-3038", "runtime": 50, "cores": 300, "data_deps": {"task-3033": 300, "task-3034": 300, "task-3035": 300, "task-3036": 300}}, "task-3039": {"id": "task-3039", "runtime": 645, "cores": 300, "data_deps": {"task-3033": 300, "task-3034": 300, "task-3035": 300, "task-3036": 300}}, "task-3040": {"id": "task-3040", "runtime": 123, "cores": 300, "data_deps": {"task-3033": 300, "task-3034": 300, "task-3035": 300, "task-3036": 300}}, "task-3041": {"id": "task-3041", "runtime": 589, "cores": 300, "data_deps": {"task-3037": 300, "task-3038": 300, "task-3039": 300, "task-3040": 300}}, "task-3042": {"id": "task-3042", "runtime": 132, "cores": 300, "data_deps": {"task-3037": 300, "task-3038": 300, "task-3039": 300, "task-3040": 300}}, "task-3043": {"id": "task-3043", "runtime": 146, "cores": 300, "data_deps": {"task-3037": 300, "task-3038": 300, "task-3039": 300, "task-3040": 300}}, "task-3044": {"id": "task-3044", "runtime": 2093, "cores": 300, "data_deps": {"task-3037": 300, "task-3038": 300, "task-3039": 300, "task-3040": 300}}}