{"task-2547": {"id": "task-2547", "runtime": 223433, "cores": 600, "data_deps": {}}, "task-2548": {"id": "task-2548", "runtime": 36000, "cores": 48, "data_deps": {}}, "task-2549": {"id": "task-2549", "runtime": 71, "cores": 1, "data_deps": {}}, "task-2550": {"id": "task-2550", "runtime": 1305, "cores": 1, "data_deps": {"task-2547": 600, "task-2548": 48, "task-2549": 1}}, "task-2551": {"id": "task-2551", "runtime": 29067, "cores": 2000, "data_deps": {"task-2547": 600, "task-2548": 48, "task-2549": 1}}, "task-2552": {"id": "task-2552", "runtime": 376, "cores": 1, "data_deps": {"task-2547": 600, "task-2548": 48, "task-2549": 1}}, "task-2553": {"id": "task-2553", "runtime": 17169, "cores": 1, "data_deps": {"task-2550": 1, "task-2551": 2000, "task-2552": 1}}, "task-2554": {"id": "task-2554", "runtime": 16865, "cores": 1, "data_deps": {"task-2550": 1, "task-2551": 2000, "task-2552": 1}}, "task-2555": {"id": "task-2555", "runtime": 16925, "cores": 1, "data_deps": {"task-2550": 1, "task-2551": 2000, "task-2552": 1}}, "task-2556": {"id": "task-2556", "runtime": 16742, "cores": 1, "data_deps": {"task-2550": 1, "task-2551": 2000, "task-2552": 1}}}