{"task-354": {"id": "task-354", "runtime": 53, "cores": 1, "data_deps": {}}, "task-355": {"id": "task-355", "runtime": 178, "cores": 1, "data_deps": {}}, "task-356": {"id": "task-356", "runtime": 146, "cores": 2, "data_deps": {}}, "task-357": {"id": "task-357", "runtime": 165, "cores": 1, "data_deps": {"task-354": 1, "task-355": 1, "task-356": 2}}, "task-358": {"id": "task-358", "runtime": 4638, "cores": 1, "data_deps": {"task-354": 1, "task-355": 1, "task-356": 2}}, "task-359": {"id": "task-359", "runtime": 180, "cores": 4, "data_deps": {"task-354": 1, "task-355": 1, "task-356": 2}}, "task-360": {"id": "task-360", "runtime": 172800, "cores": 1000, "data_deps": {"task-357": 1, "task-358": 1, "task-359": 4}}, "task-361": {"id": "task-361", "runtime": 118685, "cores": 1000, "data_deps": {"task-357": 1, "task-358": 1, "task-359": 4}}, "task-362": {"id": "task-362", "runtime": 183, "cores": 4, "data_deps": {"task-357": 1, "task-358": 1, "task-359": 4}}, "task-363": {"id": "task-363", "runtime": 184, "cores": 4, "data_deps": {"task-360": 1000, "task-361": 1000, "task-362": 4}}, "task-364": {"id": "task-364", "runtime": 190, "cores": 4, "data_deps": {"task-360": 1000, "task-361": 1000, "task-362": 4}}, "task-365": {"id": "task-365", "runtime": 178, "cores": 4, "data_deps": {"task-360": 1000, "task-361": 1000, "task-362": 4}}, "task-366": {"id": "task-366", "runtime": 166950, "cores": 15000, "data_deps": {"task-360": 1000, "task-361": 1000, "task-362": 4}}}