{
    "task-395": {
        "id": "task-395",
        "runtime": 208,
        "cores": 220,
        "data_deps": {}
    },
    "task-396": {
        "id": "task-396",
        "runtime": 208,
        "cores": 240,
        "data_deps": {
            "task-395": 220
        }
    },
    "task-397": {
        "id": "task-397",
        "runtime": 137,
        "cores": 200,
        "data_deps": {
            "task-396": 240
        }
    },
    "task-398": {
        "id": "task-398",
        "runtime": 115,
        "cores": 1000,
        "data_deps": {
            "task-397": 200
        }
    },
    "task-399": {
        "id": "task-399",
        "runtime": 126,
        "cores": 2000,
        "data_deps": {
            "task-398": 1000
        }
    },
    "task-400": {
        "id": "task-400",
        "runtime": 73,
        "cores": 200,
        "data_deps": {
            "task-399": 2000
        }
    }
}