{
    "task-206": {
        "id": "task-206",
        "runtime": 57750,
        "cores": 100,
        "data_deps": {}
    },
    "task-207": {
        "id": "task-207",
        "runtime": 48529,
        "cores": 100,
        "data_deps": {
            "task-206": 100
        }
    },
    "task-208": {
        "id": "task-208",
        "runtime": 44110,
        "cores": 100,
        "data_deps": {
            "task-207": 100
        }
    },
    "task-209": {
        "id": "task-209",
        "runtime": 96,
        "cores": 100,
        "data_deps": {
            "task-208": 100
        }
    },
    "task-210": {
        "id": "task-210",
        "runtime": 93224,
        "cores": 500,
        "data_deps": {
            "task-209": 100
        }
    },
    "task-211": {
        "id": "task-211",
        "runtime": 42539,
        "cores": 100,
        "data_deps": {
            "task-210": 500
        }
    }
}